LICENSE.txt
MANIFEST.in
README.md
RELEASE.md
requirements.txt
setup.py
vlib/__init__.py
vlib/attributes.py
vlib/cli.py
vlib/colors.py
vlib/conf.py
vlib/datarecord.py
vlib/datatable.py
vlib/db.py
vlib/elapsetime.py
vlib/entities.py
vlib/logger.py
vlib/odict.py
vlib/shell.py
vlib/singleton.py
vlib/sqlutils.py
vlib/utils.py
vlib/vlibconf.template.yml
vlib.egg-info/PKG-INFO
vlib.egg-info/SOURCES.txt
vlib.egg-info/dependency_links.txt
vlib.egg-info/top_level.txt