Metadata-Version: 1.1
Name: vlib
Version: 1.3.2
Summary: vlib core libraries
Home-page: https://github.com/dlink/vlib
Author: David Link
Author-email: dvlink@gmail.com
License: GNU General Public License (GPL)
Keywords: database,logging,config,orm,odict
Platform: UNKNOWN
Classifier: Development Status :: 5 - Production/Stable
Classifier: Intended Audience :: Developers
Classifier: License :: OSI Approved :: GNU General Public License (GPL)
Classifier: Programming Language :: Python :: 2.7
Classifier: Topic :: Database
Classifier: Topic :: Software Development :: Libraries
